thread_safe_vk-0.1.4.dist-info/metadata.json
thread_safe_vk-0.1.4.dist-info/pbr.json
thread_safe_vk-0.1.4.dist-info/RECORD
thread_safe_vk-0.1.4.dist-info/WHEEL
thread_safe_vk-0.1.4.dist-info/top_level.txt
thread_safe_vk-0.1.4.dist-info/METADATA
thread_safe_vk-0.1.4.dist-info/DESCRIPTION.rst
thread_safe_vk/__init__.py
thread_safe_vk/vk_api.py
thread_safe_vk/utils/__init__.py
thread_safe_vk/utils/decorators.py
