Metadata-Version: 2.0
Name: thread-safe-vk
Version: 0.1.4
Summary: UNKNOWN
Home-page: https://github.com/soon/ThreadSafeVk
Author: Andrew Kuchev
Author-email: kuchevad@gmail.com
License: MIT
Keywords: thread safe vk api
Platform: UNKNOWN
Classifier: Development Status :: 3 - Alpha
Classifier: Environment :: Console
Classifier: License :: OSI Approved :: MIT License
Classifier: Operating System :: OS Independent
Classifier: Programming Language :: Python :: 3
Classifier: Programming Language :: Python :: 2
Classifier: Topic :: Utilities
Requires-Dist: vk
